PBFUS1/__init__.py
PBFUS1/config.yaml
PBFUS1/data_loader.py
PBFUS1/metadata.py
PBFUS1-1.0.0.dist-info/LICENSE.TXT
PBFUS1-1.0.0.dist-info/METADATA
PBFUS1-1.0.0.dist-info/WHEEL
PBFUS1-1.0.0.dist-info/top_level.txt
PBFUS1-1.0.0.dist-info/RECORD
