Metadata-Version: 2.1
Name: PBFUS1
Version: 1.0.0
Summary: A package to handle and process ultrasound image datasets of fetal planes
Author: Juan Pablo Barrientos
Author-email: juan.barrientos@galileo.edu
Classifier: Programming Language :: Python :: 3
Classifier: License :: OSI Approved :: MIT License
Classifier: Operating System :: OS Independent
Requires-Python: >=3.6
License-File: LICENSE.TXT
Requires-Dist: opencv-python
Requires-Dist: pandas
Requires-Dist: matplotlib
Requires-Dist: PyYAML
Requires-Dist: requests
Requires-Dist: tqdm
